wechat_publisher/__init__.py
wechat_publisher/article_types.py
wechat_publisher/core.py
wechat_publisher/html_utils.py
wechat_publisher/image.py
wechat_publisher-0.1.1.dist-info/LICENSE
wechat_publisher-0.1.1.dist-info/METADATA
wechat_publisher-0.1.1.dist-info/WHEEL
wechat_publisher-0.1.1.dist-info/top_level.txt
wechat_publisher-0.1.1.dist-info/RECORD
